{
  "data": {
    "tags": {
      "page": 45,
      "perPage": 100,
      "results": [
        {
          "category": false,
          "createdAt": "2026-05-11T10:04:36Z",
          "creatorId": "a2d00571-127b-4081-a210-89b313354ce5",
          "id": "22ce0e15-e9e8-4432-a04c-8d1d3a6c11fb",
          "name": "dieselpunk",
          "namespace": "artwork",
          "pendingRevisions": false,
          "slug": "dieselpunk",
          "status": "GOOD_STANDING",
          "type": "ILLUSTRATION_TAG",
          "hasExemplaryTagging": false,
          "description": null,
          "taggingCount": 1
        },
        {
          "category": false,
          "createdAt": "2025-07-11T09:55:37Z",
          "creatorId": "1cd71b69-3eea-457f-a8f1-b004599098f5",
          "id": "08c3acef-f62b-45b2-ae54-0b2bb56b739c",
          "name": "differently named lands matter",
          "namespace": "card",
          "pendingRevisions": false,
          "slug": "differently-named-lands-matter",
          "status": "GOOD_STANDING",
          "type": "ORACLE_CARD_TAG",
          "hasExemplaryTagging": false,
          "description": "These cards want you to have multiple lands with different names.",
          "taggingCount": 8
        },
        {
          "category": false,
          "createdAt": "2022-07-01T01:30:14Z",
          "creatorId": "c5946e26-2a88-4794-ae92-2ad5b6bbcbd9",
          "id": "66fade9c-5395-4400-a4a5-923175a63eab",
          "name": "dig",
          "namespace": "artwork",
          "pendingRevisions": false,
          "slug": "dig",
          "status": "GOOD_STANDING",
          "type": "ILLUSTRATION_TAG",
          "hasExemplaryTagging": false,
          "description": null,
          "taggingCount": 1
        },
        {
          "category": false,
          "createdAt": "2018-04-28T15:49:54Z",
          "creatorId": "00000000-0000-0000-0000-000000000000",
          "id": "154cef07-0c68-412a-a4d7-fdf0c2aab38c",
          "name": "digging",
          "namespace": "artwork",
          "pendingRevisions": false,
          "slug": "digging",
          "status": "GOOD_STANDING",
          "type": "ILLUSTRATION_TAG",
          "hasExemplaryTagging": false,
          "description": null,
          "taggingCount": 23
        },
        {
          "category": false,
          "createdAt": "2023-04-11T18:22:03Z",
          "creatorId": "65b51c82-08d5-4c14-b00f-277dc5f3c720",
          "id": "aba4e995-d9d7-4b28-aa0d-5114b6c2f179",
          "name": "digital only artwork",
          "namespace": "artwork",
          "pendingRevisions": false,
          "slug": "digital-only-artwork",
          "status": "GOOD_STANDING",
          "type": "ILLUSTRATION_TAG",
          "hasExemplaryTagging": false,
          "description": "Card art that is currently only available in digital games such as Arena.",
          "taggingCount": 1147
        },
        {
          "category": false,
          "createdAt": "2026-03-02T14:13:04Z",
          "creatorId": "732149b0-331a-4527-9335-466be0314fdd",
          "id": "aa1d20fe-4b9b-4f0f-ada7-db0df9ddaf2e",
          "name": "digital-only mechanics",
          "namespace": "card",
          "pendingRevisions": false,
          "slug": "digital-only-mechanics",
          "status": "GOOD_STANDING",
          "type": "ORACLE_CARD_TAG",
          "hasExemplaryTagging": false,
          "description": "Cards with mechanics designed for the digital environment of Magic Arena. Includes Unknown and acorn cards with mechanics equivalent to an existing Arena one.",
          "taggingCount": 307
        },
        {
          "category": false,
          "createdAt": "2018-11-16T17:28:23Z",
          "creatorId": "9b2cc036-84b1-42d2-980e-f54956fd6d1c",
          "id": "45d99a5c-aa29-44f3-b664-1de0f73e97a4",
          "name": "digital painting",
          "namespace": "artwork",
          "pendingRevisions": false,
          "slug": "digital-painting",
          "status": "GOOD_STANDING",
          "type": "ILLUSTRATION_TAG",
          "hasExemplaryTagging": false,
          "description": null,
          "taggingCount": 5477
        },
        {
          "category": false,
          "createdAt": "2024-11-06T05:24:55Z",
          "creatorId": "1f9672cf-0297-4dd9-9cc5-da7a56c9ad70",
          "id": "fde52f11-9c16-4cfa-80ca-f0636864e727",
          "name": "digital replacement",
          "namespace": "card",
          "pendingRevisions": false,
          "slug": "digital-replacement",
          "status": "GOOD_STANDING",
          "type": "ORACLE_CARD_TAG",
          "hasExemplaryTagging": false,
          "description": null,
          "taggingCount": 1
        },
        {
          "category": false,
          "createdAt": "2018-04-28T15:49:54Z",
          "creatorId": "bc32c722-34b5-40cd-a4ec-cc2fc963a521",
          "id": "308a7814-e05a-4730-8096-7b2577045d97",
          "name": "digital tablet",
          "namespace": "artwork",
          "pendingRevisions": false,
          "slug": "digital-tablet",
          "status": "GOOD_STANDING",
          "type": "ILLUSTRATION_TAG",
          "hasExemplaryTagging": true,
          "description": null,
          "taggingCount": 7
        },
        {
          "category": false,
          "createdAt": "2025-12-17T19:25:16Z",
          "creatorId": "1f9672cf-0297-4dd9-9cc5-da7a56c9ad70",
          "id": "2117ae16-a809-48aa-ab7c-5294b6fa4403",
          "name": "digital to paper",
          "namespace": "card",
          "pendingRevisions": false,
          "slug": "digital-to-paper",
          "status": "GOOD_STANDING",
          "type": "ORACLE_CARD_TAG",
          "hasExemplaryTagging": true,
          "description": "These cards were originally created for a set that did not see a physical printing, but were later printed in paper.",
          "taggingCount": 13
        },
        {
          "category": true,
          "createdAt": "2018-10-04T14:05:14Z",
          "creatorId": "00000000-0000-0000-0000-000000000000",
          "id": "af91a1e9-b81a-424d-bffb-a5ebe021802f",
          "name": "dilemma",
          "namespace": "card",
          "pendingRevisions": false,
          "slug": "dilemma",
          "status": "GOOD_STANDING",
          "type": "ORACLE_CARD_TAG",
          "hasExemplaryTagging": false,
          "description": "Effects that give you two equally bad choices.",
          "taggingCount": 0
        },
        {
          "category": false,
          "createdAt": "2022-05-21T11:15:52Z",
          "creatorId": "3d28157a-b852-4fd5-8fc6-a419b718949a",
          "id": "dc3dba75-70a2-4965-ae15-21d790bbd756",
          "name": "dillard portyr",
          "namespace": "artwork",
          "pendingRevisions": false,
          "slug": "dillard-portyr",
          "status": "GOOD_STANDING",
          "type": "ILLUSTRATION_TAG",
          "hasExemplaryTagging": false,
          "description": null,
          "taggingCount": 2
        },
        {
          "category": false,
          "createdAt": "2019-07-19T16:21:49Z",
          "creatorId": "876dc96d-81c6-470a-931b-40a007e06c5c",
          "id": "a0ad276e-c98b-405e-8c7f-764bf264c2b5",
          "name": "dime",
          "namespace": "artwork",
          "pendingRevisions": false,
          "slug": "dime",
          "status": "GOOD_STANDING",
          "type": "ILLUSTRATION_TAG",
          "hasExemplaryTagging": false,
          "description": null,
          "taggingCount": 1
        },
        {
          "category": false,
          "createdAt": "2026-02-21T14:11:03Z",
          "creatorId": "3576c04a-0454-4461-96f8-a41251908662",
          "id": "8c2f8997-7c1c-4915-a1b1-ebeadce4f5d1",
          "name": "dimension x",
          "namespace": "artwork",
          "pendingRevisions": false,
          "slug": "dimension-x",
          "status": "GOOD_STANDING",
          "type": "ILLUSTRATION_TAG",
          "hasExemplaryTagging": false,
          "description": null,
          "taggingCount": 7
        },
        {
          "category": false,
          "createdAt": "2018-04-28T15:49:54Z",
          "creatorId": "00000000-0000-0000-0000-000000000000",
          "id": "eccc8504-7727-4370-808b-af9aff0b706b",
          "name": "dimir",
          "namespace": "artwork",
          "pendingRevisions": false,
          "slug": "dimir",
          "status": "GOOD_STANDING",
          "type": "ILLUSTRATION_TAG",
          "hasExemplaryTagging": false,
          "description": null,
          "taggingCount": 127
        },
        {
          "category": false,
          "createdAt": "2018-09-22T19:29:29Z",
          "creatorId": "1cd71b69-3eea-457f-a8f1-b004599098f5",
          "id": "c012b45e-2cb5-4b6c-aae0-45450b303706",
          "name": "dimir spybug",
          "namespace": "artwork",
          "pendingRevisions": false,
          "slug": "dimir-spybug",
          "status": "GOOD_STANDING",
          "type": "ILLUSTRATION_TAG",
          "hasExemplaryTagging": false,
          "description": null,
          "taggingCount": 2
        },
        {
          "category": false,
          "createdAt": "2018-04-28T15:49:54Z",
          "creatorId": "00000000-0000-0000-0000-000000000000",
          "id": "1f9597c0-40ee-42e9-86b0-b708fef10209",
          "name": "dimir symbol",
          "namespace": "artwork",
          "pendingRevisions": false,
          "slug": "dimir-symbol",
          "status": "GOOD_STANDING",
          "type": "ILLUSTRATION_TAG",
          "hasExemplaryTagging": true,
          "description": null,
          "taggingCount": 36
        },
        {
          "category": false,
          "createdAt": "2021-03-30T15:28:20Z",
          "creatorId": "c5946e26-2a88-4794-ae92-2ad5b6bbcbd9",
          "id": "70f35c49-0b45-43fc-b57f-4801a6154441",
          "name": "dina",
          "namespace": "artwork",
          "pendingRevisions": false,
          "slug": "dina",
          "status": "GOOD_STANDING",
          "type": "ILLUSTRATION_TAG",
          "hasExemplaryTagging": true,
          "description": null,
          "taggingCount": 12
        },
        {
          "category": false,
          "createdAt": "2022-02-20T01:53:28Z",
          "creatorId": "876dc96d-81c6-470a-931b-40a007e06c5c",
          "id": "672011cd-5022-4fd4-867b-1921e14bc8d3",
          "name": "dinghy",
          "namespace": "artwork",
          "pendingRevisions": false,
          "slug": "dinghy",
          "status": "GOOD_STANDING",
          "type": "ILLUSTRATION_TAG",
          "hasExemplaryTagging": false,
          "description": null,
          "taggingCount": 6
        },
        {
          "category": false,
          "createdAt": "2018-04-28T15:49:54Z",
          "creatorId": "00000000-0000-0000-0000-000000000000",
          "id": "109194a6-93c3-4aee-af5e-960ba1c0f10b",
          "name": "dinosaur",
          "namespace": "artwork",
          "pendingRevisions": false,
          "slug": "dinosaur",
          "status": "GOOD_STANDING",
          "type": "ILLUSTRATION_TAG",
          "hasExemplaryTagging": false,
          "description": "🦖🦕",
          "taggingCount": 298
        },
        {
          "category": false,
          "createdAt": "2026-05-09T12:35:53Z",
          "creatorId": "c8753193-402a-4d49-abd3-f3bf510f2d51",
          "id": "b9bf1730-4b34-4ce8-83fa-a49d3046773d",
          "name": "dinosaur person",
          "namespace": "artwork",
          "pendingRevisions": false,
          "slug": "dinosaur-person",
          "status": "GOOD_STANDING",
          "type": "ILLUSTRATION_TAG",
          "hasExemplaryTagging": false,
          "description": null,
          "taggingCount": 0
        },
        {
          "category": false,
          "createdAt": "2023-10-25T13:26:03Z",
          "creatorId": "bbf8a603-4587-416b-b976-92b7f19468c3",
          "id": "25f2d075-c8f3-431f-9570-dfe76b6bc31a",
          "name": "dinosaur skull",
          "namespace": "artwork",
          "pendingRevisions": false,
          "slug": "dinosaur-skull",
          "status": "GOOD_STANDING",
          "type": "ILLUSTRATION_TAG",
          "hasExemplaryTagging": false,
          "description": "Contains a recognizable dinosaur skull.",
          "taggingCount": 12
        },
        {
          "category": false,
          "createdAt": "2025-05-26T06:18:40Z",
          "creatorId": "732149b0-331a-4527-9335-466be0314fdd",
          "id": "5f8ea789-708d-4e8d-a324-dc8419dcb580",
          "name": "dion lesage",
          "namespace": "artwork",
          "pendingRevisions": false,
          "slug": "dion-lesage",
          "status": "GOOD_STANDING",
          "type": "ILLUSTRATION_TAG",
          "hasExemplaryTagging": false,
          "description": null,
          "taggingCount": 2
        },
        {
          "category": false,
          "createdAt": "2024-10-30T19:02:29Z",
          "creatorId": "3584e47b-72d6-49ef-9c20-35967bbc056b",
          "id": "0bd4f2a3-f04f-4944-9d97-cabf4edd3a5b",
          "name": "dionus",
          "namespace": "artwork",
          "pendingRevisions": false,
          "slug": "dionus",
          "status": "GOOD_STANDING",
          "type": "ILLUSTRATION_TAG",
          "hasExemplaryTagging": false,
          "description": null,
          "taggingCount": 1
        },
        {
          "category": false,
          "createdAt": "2026-05-02T04:10:33Z",
          "creatorId": "1f9672cf-0297-4dd9-9cc5-da7a56c9ad70",
          "id": "2732cf13-1eb5-4e8f-b6fb-253164b90745",
          "name": "diorama",
          "namespace": "artwork",
          "pendingRevisions": false,
          "slug": "diorama",
          "status": "GOOD_STANDING",
          "type": "ILLUSTRATION_TAG",
          "hasExemplaryTagging": false,
          "description": null,
          "taggingCount": 1
        },
        {
          "category": false,
          "createdAt": "2020-05-10T14:04:52Z",
          "creatorId": "3d28157a-b852-4fd5-8fc6-a419b718949a",
          "id": "dc89bfec-9155-432f-9169-d33e5b58ee5a",
          "name": "dire fleet",
          "namespace": "artwork",
          "pendingRevisions": false,
          "slug": "dire-fleet",
          "status": "GOOD_STANDING",
          "type": "ILLUSTRATION_TAG",
          "hasExemplaryTagging": false,
          "description": null,
          "taggingCount": 19
        },
        {
          "category": false,
          "createdAt": "2021-09-11T01:03:23Z",
          "creatorId": "4d16b85d-9230-4cba-ba62-ff3d81f9692e",
          "id": "a47b3392-c5cf-410b-8362-8451a11f490e",
          "name": "dire-strain werewolf",
          "namespace": "artwork",
          "pendingRevisions": false,
          "slug": "dire-strain-werewolf",
          "status": "GOOD_STANDING",
          "type": "ILLUSTRATION_TAG",
          "hasExemplaryTagging": false,
          "description": null,
          "taggingCount": 10
        },
        {
          "category": false,
          "createdAt": "2018-04-28T15:49:54Z",
          "creatorId": "f6d4c16c-c533-4c63-ac2c-cb70327b0164",
          "id": "c076d2e3-e890-440b-bb25-0d1dcae8cce5",
          "name": "dirigible",
          "namespace": "artwork",
          "pendingRevisions": false,
          "slug": "dirigible",
          "status": "GOOD_STANDING",
          "type": "ILLUSTRATION_TAG",
          "hasExemplaryTagging": false,
          "description": "Zeppelins, blimps, and similar aircraft.",
          "taggingCount": 24
        },
        {
          "category": false,
          "createdAt": "2019-12-01T17:10:11Z",
          "creatorId": "c4b03930-da67-42bb-b958-6c1637295dde",
          "id": "96d685fa-9bdb-40dd-b48d-afb8c6152e53",
          "name": "dirndl",
          "namespace": "artwork",
          "pendingRevisions": false,
          "slug": "dirndl",
          "status": "GOOD_STANDING",
          "type": "ILLUSTRATION_TAG",
          "hasExemplaryTagging": false,
          "description": "Traditional dress from germanic regions around the alps.",
          "taggingCount": 1
        },
        {
          "category": false,
          "createdAt": "2018-04-28T15:49:54Z",
          "creatorId": "7ac11fd9-234f-40cc-a038-9ccc48ad95dc",
          "id": "37f9cc3c-b1e4-4b95-81a7-8bf61000ebd8",
          "name": "dirt",
          "namespace": "artwork",
          "pendingRevisions": false,
          "slug": "dirt",
          "status": "GOOD_STANDING",
          "type": "ILLUSTRATION_TAG",
          "hasExemplaryTagging": false,
          "description": null,
          "taggingCount": 34
        },
        {
          "category": false,
          "createdAt": "2026-01-23T11:49:32Z",
          "creatorId": "732149b0-331a-4527-9335-466be0314fdd",
          "id": "4dee8ae5-6bf8-4eac-8268-3cd85351177c",
          "name": "dirtbag",
          "namespace": "artwork",
          "pendingRevisions": false,
          "slug": "dirtbag",
          "status": "GOOD_STANDING",
          "type": "ILLUSTRATION_TAG",
          "hasExemplaryTagging": false,
          "description": null,
          "taggingCount": 2
        },
        {
          "category": false,
          "createdAt": "2024-05-22T10:05:18Z",
          "creatorId": "c8753193-402a-4d49-abd3-f3bf510f2d51",
          "id": "c63263e2-796a-4b2e-b0b6-f025abd98bbb",
          "name": "disa",
          "namespace": "artwork",
          "pendingRevisions": false,
          "slug": "disa",
          "status": "GOOD_STANDING",
          "type": "ILLUSTRATION_TAG",
          "hasExemplaryTagging": false,
          "description": null,
          "taggingCount": 2
        },
        {
          "category": false,
          "createdAt": "2020-12-12T02:44:50Z",
          "creatorId": "f639c402-108f-4432-bea2-87a78428bcbf",
          "id": "6e6b37a5-ca52-43ac-8d0b-56b687a84851",
          "name": "disarmed",
          "namespace": "artwork",
          "pendingRevisions": false,
          "slug": "disarmed",
          "status": "GOOD_STANDING",
          "type": "ILLUSTRATION_TAG",
          "hasExemplaryTagging": false,
          "description": null,
          "taggingCount": 4
        },
        {
          "category": false,
          "createdAt": "2023-08-02T19:56:42Z",
          "creatorId": "862acd04-9015-40f2-84ac-8fc04edb0412",
          "id": "7d59474f-f953-4816-bf53-f42878301c0e",
          "name": "disassemble",
          "namespace": "artwork",
          "pendingRevisions": false,
          "slug": "disassemble",
          "status": "GOOD_STANDING",
          "type": "ILLUSTRATION_TAG",
          "hasExemplaryTagging": false,
          "description": null,
          "taggingCount": 2
        },
        {
          "category": false,
          "createdAt": "2018-04-28T15:49:54Z",
          "creatorId": "00000000-0000-0000-0000-000000000000",
          "id": "fce2f2c1-bb65-45e8-8c0a-dd66093067d7",
          "name": "discard",
          "namespace": "card",
          "pendingRevisions": false,
          "slug": "discard",
          "status": "GOOD_STANDING",
          "type": "ORACLE_CARD_TAG",
          "hasExemplaryTagging": true,
          "description": "Gets cards out of your opponent's hand and into their graveyard.",
          "taggingCount": 572
        },
        {
          "category": false,
          "createdAt": "2020-02-25T00:24:17Z",
          "creatorId": "1cd71b69-3eea-457f-a8f1-b004599098f5",
          "id": "7fc71046-aa54-4ca6-bb3e-7336d5d58d0f",
          "name": "discarded type matters",
          "namespace": "card",
          "pendingRevisions": false,
          "slug": "discarded-type-matters",
          "status": "GOOD_STANDING",
          "type": "ORACLE_CARD_TAG",
          "hasExemplaryTagging": false,
          "description": "The type of card you discard matters for some effect.",
          "taggingCount": 58
        },
        {
          "category": false,
          "createdAt": "2019-07-05T11:16:30Z",
          "creatorId": "fbe9a520-08bf-4c6f-8850-dd72707d0150",
          "id": "2a8357d4-cc81-4739-9582-48725b7373a9",
          "name": "discard matters",
          "namespace": "card",
          "pendingRevisions": false,
          "slug": "discard-matters",
          "status": "GOOD_STANDING",
          "type": "ORACLE_CARD_TAG",
          "hasExemplaryTagging": false,
          "description": null,
          "taggingCount": 24
        },
        {
          "category": false,
          "createdAt": "2018-04-28T15:49:54Z",
          "creatorId": "01b352ea-e5db-46df-affe-365ce2e30308",
          "id": "2af2712e-6228-4559-836f-3cdb65db1242",
          "name": "discard outlet",
          "namespace": "card",
          "pendingRevisions": false,
          "slug": "discard-outlet",
          "status": "GOOD_STANDING",
          "type": "ORACLE_CARD_TAG",
          "hasExemplaryTagging": false,
          "description": null,
          "taggingCount": 479
        },
        {
          "category": false,
          "createdAt": "2021-09-16T18:06:56Z",
          "creatorId": "494f1b56-f250-45c2-84e7-559ffdd39ffc",
          "id": "c0ecd917-798d-4b63-bdc8-813b3730651c",
          "name": "discard outlet-artifact",
          "namespace": "card",
          "pendingRevisions": false,
          "slug": "discard-outlet-artifact",
          "status": "GOOD_STANDING",
          "type": "ORACLE_CARD_TAG",
          "hasExemplaryTagging": false,
          "description": null,
          "taggingCount": 4
        },
        {
          "category": false,
          "createdAt": "2021-09-16T18:07:53Z",
          "creatorId": "494f1b56-f250-45c2-84e7-559ffdd39ffc",
          "id": "7e42bbdf-1fd9-4ede-999e-eac2c3e1f719",
          "name": "discard outlet-creature",
          "namespace": "card",
          "pendingRevisions": false,
          "slug": "discard-outlet-creature",
          "status": "GOOD_STANDING",
          "type": "ORACLE_CARD_TAG",
          "hasExemplaryTagging": false,
          "description": null,
          "taggingCount": 28
        },
        {
          "category": false,
          "createdAt": "2021-09-16T18:13:08Z",
          "creatorId": "494f1b56-f250-45c2-84e7-559ffdd39ffc",
          "id": "12b8c7ad-efd3-4e91-8e55-63cc37eac197",
          "name": "discard outlet-land",
          "namespace": "card",
          "pendingRevisions": false,
          "slug": "discard-outlet-land",
          "status": "GOOD_STANDING",
          "type": "ORACLE_CARD_TAG",
          "hasExemplaryTagging": false,
          "description": null,
          "taggingCount": 53
        },
        {
          "category": false,
          "createdAt": "2021-09-16T18:05:30Z",
          "creatorId": "494f1b56-f250-45c2-84e7-559ffdd39ffc",
          "id": "362bdc67-9bcc-4fdd-b009-482994b82737",
          "name": "discard outlet-last drawn",
          "namespace": "card",
          "pendingRevisions": false,
          "slug": "discard-outlet-last-drawn",
          "status": "GOOD_STANDING",
          "type": "ORACLE_CARD_TAG",
          "hasExemplaryTagging": false,
          "description": null,
          "taggingCount": 5
        },
        {
          "category": false,
          "createdAt": "2023-01-27T12:57:53Z",
          "creatorId": "494f1b56-f250-45c2-84e7-559ffdd39ffc",
          "id": "e558a02f-8f58-4133-a9b1-c20f0b70e6f4",
          "name": "discard outlet-nonland",
          "namespace": "card",
          "pendingRevisions": false,
          "slug": "discard-outlet-nonland",
          "status": "GOOD_STANDING",
          "type": "ORACLE_CARD_TAG",
          "hasExemplaryTagging": false,
          "description": null,
          "taggingCount": 1
        },
        {
          "category": false,
          "createdAt": "2021-07-26T18:19:06Z",
          "creatorId": "494f1b56-f250-45c2-84e7-559ffdd39ffc",
          "id": "338d1ecc-88be-451a-b744-e2cd6c6c9b33",
          "name": "discard outlet-random",
          "namespace": "card",
          "pendingRevisions": false,
          "slug": "discard-outlet-random",
          "status": "GOOD_STANDING",
          "type": "ORACLE_CARD_TAG",
          "hasExemplaryTagging": false,
          "description": null,
          "taggingCount": 45
        },
        {
          "category": false,
          "createdAt": "2018-11-25T23:40:05Z",
          "creatorId": "9b2cc036-84b1-42d2-980e-f54956fd6d1c",
          "id": "8531c88c-b912-4148-8ea1-6ba752ecec00",
          "name": "discard to exile",
          "namespace": "card",
          "pendingRevisions": false,
          "slug": "discard-to-exile",
          "status": "GOOD_STANDING",
          "type": "ORACLE_CARD_TAG",
          "hasExemplaryTagging": false,
          "description": "Put cards from the opponent's hand into exile, either permanently or by [banishing](banish-hand) them.",
          "taggingCount": 72
        },
        {
          "category": false,
          "createdAt": "2020-06-25T14:53:10Z",
          "creatorId": "494f1b56-f250-45c2-84e7-559ffdd39ffc",
          "id": "fbc5aac3-d226-458b-953d-4e724f3b83e4",
          "name": "discard to library",
          "namespace": "card",
          "pendingRevisions": false,
          "slug": "discard-to-library",
          "status": "GOOD_STANDING",
          "type": "ORACLE_CARD_TAG",
          "hasExemplaryTagging": false,
          "description": "Put cards from the opponent's hand back into their library.",
          "taggingCount": 22
        },
        {
          "category": false,
          "createdAt": "2022-11-25T20:51:53Z",
          "creatorId": "f54feb6b-13ec-4b10-bf66-ab8328381330",
          "id": "6c9a128a-22e6-4f93-93de-aa8a0750bf73",
          "name": "discard with set's mechanic",
          "namespace": "card",
          "pendingRevisions": false,
          "slug": "discard-with-set-s-mechanic",
          "status": "GOOD_STANDING",
          "type": "ORACLE_CARD_TAG",
          "hasExemplaryTagging": true,
          "description": null,
          "taggingCount": 200
        },
        {
          "category": false,
          "createdAt": "2025-05-22T02:14:29Z",
          "creatorId": "0e9c7553-6781-4e51-9b76-799c9a32513b",
          "id": "a9df3c3b-710f-46a5-852c-630d0e7af39c",
          "name": "disco ball",
          "namespace": "artwork",
          "pendingRevisions": false,
          "slug": "disco-ball",
          "status": "GOOD_STANDING",
          "type": "ILLUSTRATION_TAG",
          "hasExemplaryTagging": false,
          "description": null,
          "taggingCount": 3
        },
        {
          "category": false,
          "createdAt": "2022-09-19T20:45:53Z",
          "creatorId": "c5946e26-2a88-4794-ae92-2ad5b6bbcbd9",
          "id": "ac21fd02-142e-424b-a5e8-eeff1cca799b",
          "name": "disc of tzeentch",
          "namespace": "artwork",
          "pendingRevisions": false,
          "slug": "disc-of-tzeentch",
          "status": "GOOD_STANDING",
          "type": "ILLUSTRATION_TAG",
          "hasExemplaryTagging": false,
          "description": null,
          "taggingCount": 2
        },
        {
          "category": false,
          "createdAt": "2026-01-30T05:27:17Z",
          "creatorId": "f54feb6b-13ec-4b10-bf66-ab8328381330",
          "id": "201896e4-2737-450e-a014-da1003a84098",
          "name": "discord (character)",
          "namespace": "artwork",
          "pendingRevisions": false,
          "slug": "discord-character",
          "status": "GOOD_STANDING",
          "type": "ILLUSTRATION_TAG",
          "hasExemplaryTagging": false,
          "description": null,
          "taggingCount": 3
        },
        {
          "category": false,
          "createdAt": "2025-05-08T23:17:37Z",
          "creatorId": "f54feb6b-13ec-4b10-bf66-ab8328381330",
          "id": "bd38985d-b7cc-4eac-b45d-1ac0cee3b8f7",
          "name": "discount-self",
          "namespace": "card",
          "pendingRevisions": false,
          "slug": "discount-self",
          "status": "GOOD_STANDING",
          "type": "ORACLE_CARD_TAG",
          "hasExemplaryTagging": false,
          "description": "Cards that have a way to reduce their own cost",
          "taggingCount": 192
        },
        {
          "category": false,
          "createdAt": "2018-04-28T15:49:54Z",
          "creatorId": "00000000-0000-0000-0000-000000000000",
          "id": "a9985387-f7ed-4a96-86f9-84ca597b86ab",
          "name": "disease",
          "namespace": "artwork",
          "pendingRevisions": false,
          "slug": "disease",
          "status": "GOOD_STANDING",
          "type": "ILLUSTRATION_TAG",
          "hasExemplaryTagging": true,
          "description": null,
          "taggingCount": 32
        },
        {
          "category": false,
          "createdAt": "2020-10-30T20:03:14Z",
          "creatorId": "1cd71b69-3eea-457f-a8f1-b004599098f5",
          "id": "e144d652-0d0a-40f3-865f-12cdc956b33f",
          "name": "disembodied eye",
          "namespace": "artwork",
          "pendingRevisions": false,
          "slug": "disembodied-eye",
          "status": "GOOD_STANDING",
          "type": "ILLUSTRATION_TAG",
          "hasExemplaryTagging": false,
          "description": "An eye or pair of eyes disembodied, especially watching.",
          "taggingCount": 20
        },
        {
          "category": false,
          "createdAt": "2022-08-28T10:10:09Z",
          "creatorId": "9664af56-f430-449c-85b7-643c79a7c538",
          "id": "2b829575-5285-407c-bfff-ccc3324cf9af",
          "name": "disembodied hand",
          "namespace": "artwork",
          "pendingRevisions": false,
          "slug": "disembodied-hand",
          "status": "GOOD_STANDING",
          "type": "ILLUSTRATION_TAG",
          "hasExemplaryTagging": false,
          "description": null,
          "taggingCount": 9
        },
        {
          "category": false,
          "createdAt": "2018-04-28T15:49:54Z",
          "creatorId": "00000000-0000-0000-0000-000000000000",
          "id": "6bb46e61-efa1-40f9-8c76-2643677318b4",
          "name": "disembodied head",
          "namespace": "artwork",
          "pendingRevisions": false,
          "slug": "disembodied-head",
          "status": "GOOD_STANDING",
          "type": "ILLUSTRATION_TAG",
          "hasExemplaryTagging": false,
          "description": null,
          "taggingCount": 76
        },
        {
          "category": false,
          "createdAt": "2018-08-22T09:45:02Z",
          "creatorId": "1cd71b69-3eea-457f-a8f1-b004599098f5",
          "id": "a4f28106-20bf-4ff5-b756-d87b1ead87f0",
          "name": "disembodied limb",
          "namespace": "artwork",
          "pendingRevisions": false,
          "slug": "disembodied-limb",
          "status": "GOOD_STANDING",
          "type": "ILLUSTRATION_TAG",
          "hasExemplaryTagging": false,
          "description": null,
          "taggingCount": 26
        },
        {
          "category": false,
          "createdAt": "2022-12-03T21:01:17Z",
          "creatorId": "f54feb6b-13ec-4b10-bf66-ab8328381330",
          "id": "5c75484f-369a-4021-808b-ebf854d1269a",
          "name": "disenchant/naturalize",
          "namespace": "card",
          "pendingRevisions": false,
          "slug": "disenchant-naturalize",
          "status": "GOOD_STANDING",
          "type": "ORACLE_CARD_TAG",
          "hasExemplaryTagging": true,
          "description": "Cards that remove artifacts and/or enchantments.",
          "taggingCount": 173
        },
        {
          "category": false,
          "createdAt": "2020-08-09T23:27:27Z",
          "creatorId": "f0dd9761-f91c-4b52-889d-b1d38bd18b09",
          "id": "a79aa9a4-c958-4476-b3e4-fc83783f1ea1",
          "name": "disguise",
          "namespace": "artwork",
          "pendingRevisions": false,
          "slug": "disguise",
          "status": "GOOD_STANDING",
          "type": "ILLUSTRATION_TAG",
          "hasExemplaryTagging": false,
          "description": null,
          "taggingCount": 9
        },
        {
          "category": false,
          "createdAt": "2018-04-28T15:49:54Z",
          "creatorId": "00000000-0000-0000-0000-000000000000",
          "id": "a977a535-8d31-4808-adf4-e8d5facb0723",
          "name": "disgust",
          "namespace": "artwork",
          "pendingRevisions": false,
          "slug": "disgust",
          "status": "GOOD_STANDING",
          "type": "ILLUSTRATION_TAG",
          "hasExemplaryTagging": false,
          "description": null,
          "taggingCount": 7
        },
        {
          "category": false,
          "createdAt": "2018-05-12T19:22:27Z",
          "creatorId": "1cd71b69-3eea-457f-a8f1-b004599098f5",
          "id": "6a2b915b-3a82-4b55-9aee-d7ee45887530",
          "name": "disintegrate",
          "namespace": "artwork",
          "pendingRevisions": false,
          "slug": "disintegrate",
          "status": "GOOD_STANDING",
          "type": "ILLUSTRATION_TAG",
          "hasExemplaryTagging": false,
          "description": null,
          "taggingCount": 53
        },
        {
          "category": false,
          "createdAt": "2019-07-02T10:02:46Z",
          "creatorId": "1cd71b69-3eea-457f-a8f1-b004599098f5",
          "id": "30110095-c991-4fb0-904a-dbae05f4c266",
          "name": "disintegrate",
          "namespace": "card",
          "pendingRevisions": false,
          "slug": "disintegrate",
          "status": "GOOD_STANDING",
          "type": "ORACLE_CARD_TAG",
          "hasExemplaryTagging": true,
          "description": "Damaged creatures are exiled instead of dying.",
          "taggingCount": 60
        },
        {
          "category": false,
          "createdAt": "2021-12-22T07:01:11Z",
          "creatorId": "4e7657a7-8c47-4f69-a7d8-6dc6f19026f3",
          "id": "313c4804-0127-48f2-8588-9a872bf6c877",
          "name": "dismantle",
          "namespace": "artwork",
          "pendingRevisions": false,
          "slug": "dismantle",
          "status": "GOOD_STANDING",
          "type": "ILLUSTRATION_TAG",
          "hasExemplaryTagging": false,
          "description": null,
          "taggingCount": 4
        },
        {
          "category": false,
          "createdAt": "2018-10-27T19:31:10Z",
          "creatorId": "876dc96d-81c6-470a-931b-40a007e06c5c",
          "id": "7f6ee0e0-558d-48bd-828a-c4ca290cf2d9",
          "name": "dismemberment",
          "namespace": "artwork",
          "pendingRevisions": false,
          "slug": "dismemberment",
          "status": "GOOD_STANDING",
          "type": "ILLUSTRATION_TAG",
          "hasExemplaryTagging": false,
          "description": null,
          "taggingCount": 24
        },
        {
          "category": false,
          "createdAt": "2022-05-28T17:08:40Z",
          "creatorId": "c5946e26-2a88-4794-ae92-2ad5b6bbcbd9",
          "id": "d5751308-bf38-430d-a845-c11e03172471",
          "name": "displacer beast",
          "namespace": "artwork",
          "pendingRevisions": false,
          "slug": "displacer-beast",
          "status": "GOOD_STANDING",
          "type": "ILLUSTRATION_TAG",
          "hasExemplaryTagging": true,
          "description": null,
          "taggingCount": 8
        },
        {
          "category": false,
          "createdAt": "2019-02-25T20:40:48Z",
          "creatorId": "7ac11fd9-234f-40cc-a038-9ccc48ad95dc",
          "id": "503eca6f-4cd5-46a6-93f6-a99f931c601d",
          "name": "display case",
          "namespace": "artwork",
          "pendingRevisions": false,
          "slug": "display-case",
          "status": "GOOD_STANDING",
          "type": "ILLUSTRATION_TAG",
          "hasExemplaryTagging": false,
          "description": null,
          "taggingCount": 13
        },
        {
          "category": false,
          "createdAt": "2018-04-28T15:49:54Z",
          "creatorId": "00000000-0000-0000-0000-000000000000",
          "id": "44915375-7d74-4d2f-923b-deaa26d30588",
          "name": "dissolve",
          "namespace": "artwork",
          "pendingRevisions": false,
          "slug": "dissolve",
          "status": "GOOD_STANDING",
          "type": "ILLUSTRATION_TAG",
          "hasExemplaryTagging": false,
          "description": null,
          "taggingCount": 12
        },
        {
          "category": false,
          "createdAt": "2021-06-07T08:18:32Z",
          "creatorId": "98e0398f-04eb-43de-a4c4-f78701218af7",
          "id": "20ce4f66-09d1-43c0-84d8-835dc92130bd",
          "name": "distant cityscape",
          "namespace": "artwork",
          "pendingRevisions": false,
          "slug": "distant-cityscape",
          "status": "GOOD_STANDING",
          "type": "ILLUSTRATION_TAG",
          "hasExemplaryTagging": false,
          "description": null,
          "taggingCount": 13
        },
        {
          "category": false,
          "createdAt": "2019-10-21T02:29:43Z",
          "creatorId": "ba3958bb-b7c8-47b0-b343-62c20c3e2a5a",
          "id": "177e8adf-25a7-46e5-8bb8-1f81ff7a1884",
          "name": "distinct echo cost",
          "namespace": "card",
          "pendingRevisions": false,
          "slug": "distinct-echo-cost",
          "status": "GOOD_STANDING",
          "type": "ORACLE_CARD_TAG",
          "hasExemplaryTagging": false,
          "description": "Cards where the echo cost is different from the casting cost",
          "taggingCount": 11
        },
        {
          "category": false,
          "createdAt": "2019-07-27T01:36:10Z",
          "creatorId": "01e1950e-8d6f-4fa9-b000-93d5d051193a",
          "id": "ea85d7d4-e462-47b3-bb8c-01042dbe2ce5",
          "name": "distortion",
          "namespace": "artwork",
          "pendingRevisions": false,
          "slug": "distortion",
          "status": "GOOD_STANDING",
          "type": "ILLUSTRATION_TAG",
          "hasExemplaryTagging": false,
          "description": null,
          "taggingCount": 20
        },
        {
          "category": false,
          "createdAt": "2025-10-05T03:47:33Z",
          "creatorId": "3576c04a-0454-4461-96f8-a41251908662",
          "id": "7033acaf-209f-430e-adb5-d195bb801117",
          "name": "district of columbia",
          "namespace": "artwork",
          "pendingRevisions": false,
          "slug": "district-of-columbia",
          "status": "GOOD_STANDING",
          "type": "ILLUSTRATION_TAG",
          "hasExemplaryTagging": false,
          "description": null,
          "taggingCount": 1
        },
        {
          "category": false,
          "createdAt": "2021-05-20T19:28:04Z",
          "creatorId": "0c340d73-7969-4004-827c-bcb46c6f50ad",
          "id": "9a4ff7b9-1acb-4753-95ef-242af1428564",
          "name": "ditch hand",
          "namespace": "card",
          "pendingRevisions": false,
          "slug": "ditch-hand",
          "status": "GOOD_STANDING",
          "type": "ORACLE_CARD_TAG",
          "hasExemplaryTagging": false,
          "description": "Cards that let you get rid of your current hand in some way or other.",
          "taggingCount": 138
        },
        {
          "category": false,
          "createdAt": "2018-04-28T15:49:54Z",
          "creatorId": "00000000-0000-0000-0000-000000000000",
          "id": "c377c854-fa3d-4ef0-9933-50192510d9f7",
          "name": "dive",
          "namespace": "artwork",
          "pendingRevisions": false,
          "slug": "dive",
          "status": "GOOD_STANDING",
          "type": "ILLUSTRATION_TAG",
          "hasExemplaryTagging": false,
          "description": null,
          "taggingCount": 16
        },
        {
          "category": false,
          "createdAt": "2018-09-15T18:48:19Z",
          "creatorId": "1cd71b69-3eea-457f-a8f1-b004599098f5",
          "id": "ae69be34-f8ac-477d-b164-05aa149dcad6",
          "name": "diver helmet",
          "namespace": "artwork",
          "pendingRevisions": false,
          "slug": "diver-helmet",
          "status": "GOOD_STANDING",
          "type": "ILLUSTRATION_TAG",
          "hasExemplaryTagging": false,
          "description": null,
          "taggingCount": 10
        },
        {
          "category": false,
          "createdAt": "2026-05-18T12:30:33Z",
          "creatorId": "b795df6e-a871-4f6c-8969-a39ffad02163",
          "id": "0bb5679e-734c-4e4e-b9f9-7e48d8310fe8",
          "name": "divides battlefield",
          "namespace": "card",
          "pendingRevisions": false,
          "slug": "divides-battlefield",
          "status": "GOOD_STANDING",
          "type": "ORACLE_CARD_TAG",
          "hasExemplaryTagging": false,
          "description": "Cards which divide all Creatures on the Battlefield into two or more sections, which often but not always can't block each other.",
          "taggingCount": 4
        },
        {
          "category": false,
          "createdAt": "2018-12-15T18:14:43Z",
          "creatorId": "1cd71b69-3eea-457f-a8f1-b004599098f5",
          "id": "0467cac3-f1c2-422a-8125-765de2e54e2d",
          "name": "diving bell",
          "namespace": "artwork",
          "pendingRevisions": false,
          "slug": "diving-bell",
          "status": "GOOD_STANDING",
          "type": "ILLUSTRATION_TAG",
          "hasExemplaryTagging": false,
          "description": null,
          "taggingCount": 1
        },
        {
          "category": false,
          "createdAt": "2018-04-28T15:49:54Z",
          "creatorId": "cef92e32-201a-440e-8658-18fd529e4938",
          "id": "260b656f-337f-493b-8aa0-e538baad972c",
          "name": "division",
          "namespace": "card",
          "pendingRevisions": false,
          "slug": "division",
          "status": "GOOD_STANDING",
          "type": "ORACLE_CARD_TAG",
          "hasExemplaryTagging": false,
          "description": "Cards that ask for a divided value.\nFor cards that include a fractional value or a number that is not a whole number, see [non-integer](non-integer).",
          "taggingCount": 47
        },
        {
          "category": false,
          "createdAt": "2021-10-21T20:02:43Z",
          "creatorId": "e9d20f61-b40d-40fe-a04e-18ae231092b0",
          "id": "fca87b22-81a0-471b-b043-7c0d28f4dd2a",
          "name": "divvy",
          "namespace": "card",
          "pendingRevisions": false,
          "slug": "divvy",
          "status": "GOOD_STANDING",
          "type": "ORACLE_CARD_TAG",
          "hasExemplaryTagging": false,
          "description": "Cards that make you choose from two or more piles.",
          "taggingCount": 14
        },
        {
          "category": false,
          "createdAt": "2018-05-07T13:08:00Z",
          "creatorId": "dd13ef9e-27db-4de6-9105-1c380d61e169",
          "id": "1aa67eca-197c-4f45-9edb-fdd8b3b7563b",
          "name": "djeru",
          "namespace": "artwork",
          "pendingRevisions": false,
          "slug": "djeru",
          "status": "GOOD_STANDING",
          "type": "ILLUSTRATION_TAG",
          "hasExemplaryTagging": true,
          "description": null,
          "taggingCount": 8
        },
        {
          "category": false,
          "createdAt": "2018-04-28T15:49:54Z",
          "creatorId": "00000000-0000-0000-0000-000000000000",
          "id": "140a221c-3f40-46f4-8588-a701ce3e47d7",
          "name": "djinn",
          "namespace": "artwork",
          "pendingRevisions": false,
          "slug": "djinn",
          "status": "GOOD_STANDING",
          "type": "ILLUSTRATION_TAG",
          "hasExemplaryTagging": false,
          "description": null,
          "taggingCount": 121
        },
        {
          "category": false,
          "createdAt": "2025-06-23T17:25:23Z",
          "creatorId": "788e17e7-efa4-4265-bd61-026a6e0ea563",
          "id": "6b3ed5fa-dcb1-4af6-ab31-8c3ef8e85f0e",
          "name": "djose highroad",
          "namespace": "artwork",
          "pendingRevisions": false,
          "slug": "djose-highroad",
          "status": "GOOD_STANDING",
          "type": "ILLUSTRATION_TAG",
          "hasExemplaryTagging": false,
          "description": null,
          "taggingCount": 1
        },
        {
          "category": false,
          "createdAt": "2025-10-02T07:08:44Z",
          "creatorId": "732149b0-331a-4527-9335-466be0314fdd",
          "id": "635d6d88-e460-4e3a-a0ec-26112c5c7d69",
          "name": "dmitri smerdyakov",
          "namespace": "artwork",
          "pendingRevisions": false,
          "slug": "dmitri-smerdyakov",
          "status": "GOOD_STANDING",
          "type": "ILLUSTRATION_TAG",
          "hasExemplaryTagging": false,
          "description": null,
          "taggingCount": 2
        },
        {
          "category": false,
          "createdAt": "2023-02-15T19:22:55Z",
          "creatorId": "862acd04-9015-40f2-84ac-8fc04edb0412",
          "id": "726c9155-a01f-4480-b809-4ac931e6719a",
          "name": "dna strand",
          "namespace": "artwork",
          "pendingRevisions": false,
          "slug": "dna-strand",
          "status": "GOOD_STANDING",
          "type": "ILLUSTRATION_TAG",
          "hasExemplaryTagging": false,
          "description": null,
          "taggingCount": 5
        },
        {
          "category": true,
          "createdAt": "2021-06-30T12:16:53Z",
          "creatorId": "1cd71b69-3eea-457f-a8f1-b004599098f5",
          "id": "5c368f96-2e29-4d6b-930d-6cfc2af971d2",
          "name": "dnd",
          "namespace": "card",
          "pendingRevisions": false,
          "slug": "dnd",
          "status": "GOOD_STANDING",
          "type": "ORACLE_CARD_TAG",
          "hasExemplaryTagging": false,
          "description": "Cards made to reference mechanical parts of the Dungeons and Dragons TTRPG.",
          "taggingCount": 0
        },
        {
          "category": false,
          "createdAt": "2022-05-23T18:38:32Z",
          "creatorId": "c5946e26-2a88-4794-ae92-2ad5b6bbcbd9",
          "id": "68f6a394-7d5b-47cd-92d7-e5003c0bcaae",
          "name": "dnd book",
          "namespace": "card",
          "pendingRevisions": false,
          "slug": "dnd-book",
          "status": "GOOD_STANDING",
          "type": "ORACLE_CARD_TAG",
          "hasExemplaryTagging": true,
          "description": "Cards that are named after an actual printed Dungeons and Dragons book or adventure module.",
          "taggingCount": 8
        },
        {
          "category": false,
          "createdAt": "2022-04-03T22:58:19Z",
          "creatorId": "fcf25dab-00b3-4c28-92a6-76511dca1662",
          "id": "706034f6-6fb7-4ebd-b3b0-d75bf22a4374",
          "name": "dnd cartoon",
          "namespace": "artwork",
          "pendingRevisions": false,
          "slug": "dnd-cartoon",
          "status": "GOOD_STANDING",
          "type": "ILLUSTRATION_TAG",
          "hasExemplaryTagging": false,
          "description": "References to the 1983 DnD television cartoon.",
          "taggingCount": 1
        },
        {
          "category": false,
          "createdAt": "2022-05-18T17:04:11Z",
          "creatorId": "c5946e26-2a88-4794-ae92-2ad5b6bbcbd9",
          "id": "7a0d5fcf-1f73-4c45-ac27-679c93bbe9bf",
          "name": "dnd character",
          "namespace": "card",
          "pendingRevisions": false,
          "slug": "dnd-character",
          "status": "GOOD_STANDING",
          "type": "ORACLE_CARD_TAG",
          "hasExemplaryTagging": false,
          "description": "Cards that represent Dungeons and Dragons characters: name, rules text, etc. See also the [dungeons and dragons](/tags/artwork/dungeons-and-dragons) art tag.",
          "taggingCount": 208
        },
        {
          "category": false,
          "createdAt": "2021-07-18T19:05:44Z",
          "creatorId": "c5946e26-2a88-4794-ae92-2ad5b6bbcbd9",
          "id": "3a06935e-7d72-4338-ae16-b4d6882c6397",
          "name": "dnd item",
          "namespace": "card",
          "pendingRevisions": false,
          "slug": "dnd-item",
          "status": "GOOD_STANDING",
          "type": "ORACLE_CARD_TAG",
          "hasExemplaryTagging": false,
          "description": "Cards named after and representing DnD items.",
          "taggingCount": 61
        },
        {
          "category": false,
          "createdAt": "2021-07-06T12:51:50Z",
          "creatorId": "74ab3827-da23-48b0-828e-843eb928c878",
          "id": "3c9d3596-2bac-41f3-a829-99ea0ee9231b",
          "name": "dnd mechanic",
          "namespace": "card",
          "pendingRevisions": false,
          "slug": "dnd-mechanic",
          "status": "GOOD_STANDING",
          "type": "ORACLE_CARD_TAG",
          "hasExemplaryTagging": true,
          "description": "Cards named after and representing DnD mechanics.",
          "taggingCount": 57
        },
        {
          "category": false,
          "createdAt": "2021-07-18T19:07:34Z",
          "creatorId": "c5946e26-2a88-4794-ae92-2ad5b6bbcbd9",
          "id": "e12fd27b-8119-469b-832f-72e3f78fbfe1",
          "name": "dnd monster",
          "namespace": "card",
          "pendingRevisions": false,
          "slug": "dnd-monster",
          "status": "GOOD_STANDING",
          "type": "ORACLE_CARD_TAG",
          "hasExemplaryTagging": true,
          "description": "Cards named after and representing monsters from DnD.",
          "taggingCount": 97
        },
        {
          "category": false,
          "createdAt": "2021-05-10T16:22:16Z",
          "creatorId": "1cd71b69-3eea-457f-a8f1-b004599098f5",
          "id": "30aa8b34-2a80-4cfb-8dfb-8ea5757c3fa6",
          "name": "dnd multiverse",
          "namespace": "artwork",
          "pendingRevisions": false,
          "slug": "dnd-multiverse",
          "status": "GOOD_STANDING",
          "type": "ILLUSTRATION_TAG",
          "hasExemplaryTagging": false,
          "description": "Art set in the various worlds of Dungeons and Dragons, including but not limited to the [Forgotten Realms](https://tagger.scryfall.com/tags/artwork/abeir-toril).",
          "taggingCount": 2
        },
        {
          "category": false,
          "createdAt": "2021-06-30T12:16:53Z",
          "creatorId": "74ab3827-da23-48b0-828e-843eb928c878",
          "id": "95a95db2-2701-4259-a024-9389c1474e66",
          "name": "dnd spell",
          "namespace": "card",
          "pendingRevisions": false,
          "slug": "dnd-spell",
          "status": "GOOD_STANDING",
          "type": "ORACLE_CARD_TAG",
          "hasExemplaryTagging": true,
          "description": "Cards originally from DnD sets that are named after and representing DnD spells.",
          "taggingCount": 42
        },
        {
          "category": false,
          "createdAt": "2018-04-28T15:49:54Z",
          "creatorId": "00000000-0000-0000-0000-000000000000",
          "id": "c1cce931-14fd-480a-b6e6-08f36148c89d",
          "name": "dock",
          "namespace": "artwork",
          "pendingRevisions": false,
          "slug": "dock",
          "status": "GOOD_STANDING",
          "type": "ILLUSTRATION_TAG",
          "hasExemplaryTagging": false,
          "description": null,
          "taggingCount": 42
        },
        {
          "category": false,
          "createdAt": "2018-04-28T15:49:54Z",
          "creatorId": "7ac11fd9-234f-40cc-a038-9ccc48ad95dc",
          "id": "11c53dd3-dcb3-49e3-ab15-40d9314cdda6",
          "name": "doctor",
          "namespace": "artwork",
          "pendingRevisions": false,
          "slug": "doctor",
          "status": "GOOD_STANDING",
          "type": "ILLUSTRATION_TAG",
          "hasExemplaryTagging": false,
          "description": null,
          "taggingCount": 9
        },
        {
          "category": false,
          "createdAt": "2025-12-10T07:41:58Z",
          "creatorId": "732149b0-331a-4527-9335-466be0314fdd",
          "id": "342c537c-3840-4406-b834-c7f4d02043f1",
          "name": "doctor doom",
          "namespace": "artwork",
          "pendingRevisions": false,
          "slug": "doctor-doom",
          "status": "GOOD_STANDING",
          "type": "ILLUSTRATION_TAG",
          "hasExemplaryTagging": false,
          "description": null,
          "taggingCount": 5
        },
        {
          "category": false,
          "createdAt": "2025-03-06T13:36:10Z",
          "creatorId": "1cd71b69-3eea-457f-a8f1-b004599098f5",
          "id": "5b11527b-f9cf-4ece-b128-a3b584db0860",
          "name": "doctor octopus",
          "namespace": "artwork",
          "pendingRevisions": false,
          "slug": "doctor-octopus",
          "status": "GOOD_STANDING",
          "type": "ILLUSTRATION_TAG",
          "hasExemplaryTagging": false,
          "description": null,
          "taggingCount": 23
        },
        {
          "category": false,
          "createdAt": "2023-05-15T21:52:25Z",
          "creatorId": "3584e47b-72d6-49ef-9c20-35967bbc056b",
          "id": "792bb1f9-1a73-41e6-8f27-416022aa07f3",
          "name": "doctor who",
          "namespace": "artwork",
          "pendingRevisions": false,
          "slug": "doctor-who",
          "status": "GOOD_STANDING",
          "type": "ILLUSTRATION_TAG",
          "hasExemplaryTagging": false,
          "description": "A long-running sci-fi television franchise starring [the eponymous Doctor](the-doctor) and their companions.",
          "taggingCount": 112
        },
        {
          "category": false,
          "createdAt": "2023-12-02T20:55:36Z",
          "creatorId": "1f9672cf-0297-4dd9-9cc5-da7a56c9ad70",
          "id": "9706288c-c660-4c43-bc91-24c65ee74586",
          "name": "doctor who episode name",
          "namespace": "card",
          "pendingRevisions": false,
          "slug": "doctor-who-episode-name",
          "status": "GOOD_STANDING",
          "type": "ORACLE_CARD_TAG",
          "hasExemplaryTagging": false,
          "description": null,
          "taggingCount": 20
        },
        {
          "category": false,
          "createdAt": "2024-04-19T09:09:54Z",
          "creatorId": "c8753193-402a-4d49-abd3-f3bf510f2d51",
          "id": "bc3e3c0e-bb3f-41fc-bfc3-3433e819c4e9",
          "name": "doctor who episode saga",
          "namespace": "card",
          "pendingRevisions": false,
          "slug": "doctor-who-episode-saga",
          "status": "GOOD_STANDING",
          "type": "ORACLE_CARD_TAG",
          "hasExemplaryTagging": false,
          "description": "A series of cards named after and mechanically referencing various doctor who episodes.",
          "taggingCount": 19
        },
        {
          "category": false,
          "createdAt": "2018-04-28T15:49:54Z",
          "creatorId": "f639c402-108f-4432-bea2-87a78428bcbf",
          "id": "2f9d6eff-3c41-40ab-a987-cb2834c44740",
          "name": "document",
          "namespace": "artwork",
          "pendingRevisions": false,
          "slug": "document",
          "status": "GOOD_STANDING",
          "type": "ILLUSTRATION_TAG",
          "hasExemplaryTagging": false,
          "description": null,
          "taggingCount": 17
        },
        {
          "category": false,
          "createdAt": "2021-10-23T06:57:07Z",
          "creatorId": "0e9c7553-6781-4e51-9b76-799c9a32513b",
          "id": "ac319e69-c6a1-46bf-a7bd-e8c53c730a42",
          "name": "dodecahedron",
          "namespace": "artwork",
          "pendingRevisions": false,
          "slug": "dodecahedron",
          "status": "GOOD_STANDING",
          "type": "ILLUSTRATION_TAG",
          "hasExemplaryTagging": false,
          "description": null,
          "taggingCount": 5
        }
      ],
      "total": 15260
    }
  }
}
